relvalconsumer.py
relvalconsumer-2.2.1.dist-info/COPYING
relvalconsumer-2.2.1.dist-info/METADATA
relvalconsumer-2.2.1.dist-info/WHEEL
relvalconsumer-2.2.1.dist-info/top_level.txt
relvalconsumer-2.2.1.dist-info/RECORD
