Metadata-Version: 2.1
Name: relvalconsumer
Version: 2.2.1
Summary: Fedora QA wiki release validation event fedora-messaging consumer
Home-page: https://pagure.io/fedora-qa/relvalconsumer
Author: Adam Williamson
Author-email: awilliam@redhat.com
License: GPLv3+
Keywords: fedora qa mediawiki validation
Platform: UNKNOWN
Classifier: Development Status :: 5 - Production/Stable
Classifier: Topic :: Utilities
Classifier: License :: OSI Approved :: GNU General Public License v3 or later (GPLv3+)
Requires-Dist: fedfind
Requires-Dist: fedora-messaging
Requires-Dist: mwclient
Requires-Dist: setuptools
Requires-Dist: wikitcms (>=2.6.0)
